agent_os/__init__.py
agent_os/cli.py
agent_os/integrations/__init__.py
agent_os/integrations/autogen_adapter.py
agent_os/integrations/base.py
agent_os/integrations/crewai_adapter.py
agent_os/integrations/langchain_adapter.py
agent_os_kernel-1.1.0.dist-info/METADATA
agent_os_kernel-1.1.0.dist-info/WHEEL
agent_os_kernel-1.1.0.dist-info/entry_points.txt
agent_os_kernel-1.1.0.dist-info/licenses/LICENSE
agent_os_kernel-1.1.0.dist-info/RECORD
