Metadata-Version: 2.4
Name: agent-os-kernel
Version: 1.1.0
Summary: A Safety-First Kernel for Autonomous AI Agents - POSIX-inspired primitives with 0% policy violation guarantee
Project-URL: Homepage, https://github.com/imran-siddique/agent-os
Project-URL: Documentation, https://github.com/imran-siddique/agent-os/tree/master/docs
Project-URL: Repository, https://github.com/imran-siddique/agent-os
Project-URL: Bug Tracker, https://github.com/imran-siddique/agent-os/issues
Project-URL: Changelog, https://github.com/imran-siddique/agent-os/blob/master/CHANGELOG.md
Author-email: Imran Siddique <imran.siddique@microsoft.com>
Maintainer-email: Imran Siddique <imran.siddique@microsoft.com>
License-Expression: MIT
License-File: LICENSE
Keywords: agents,ai,autonomous,control-plane,governance,kernel,llm,multi-agent,posix,safety,signals,vfs
Classifier: Development Status :: 4 - Beta
Classifier: Intended Audience :: Developers
Classifier: Intended Audience :: Science/Research
Classifier: Operating System :: OS Independent
Classifier: Programming Language :: Python :: 3
Classifier: Programming Language :: Python :: 3.9
Classifier: Programming Language :: Python :: 3.10
Classifier: Programming Language :: Python :: 3.11
Classifier: Programming Language :: Python :: 3.12
Classifier: Topic :: Scientific/Engineering :: Artificial Intelligence
Classifier: Topic :: Security
Classifier: Topic :: Software Development :: Libraries :: Python Modules
Classifier: Topic :: System :: Operating System Kernels
Classifier: Typing :: Typed
Requires-Python: >=3.9
Requires-Dist: pydantic>=2.0.0
Provides-Extra: all
Requires-Dist: agent-os[dev,docs,full]; extra == 'all'
Provides-Extra: amb
Requires-Dist: aiofiles>=23.0.0; extra == 'amb'
Requires-Dist: anyio>=3.0.0; extra == 'amb'
Provides-Extra: atr
Requires-Dist: docker>=6.0.0; extra == 'atr'
Provides-Extra: caas
Requires-Dist: fastapi>=0.100.0; extra == 'caas'
Requires-Dist: numpy>=1.20.0; extra == 'caas'
Requires-Dist: pypdf2>=3.0.0; extra == 'caas'
Requires-Dist: scikit-learn>=1.0.0; extra == 'caas'
Requires-Dist: uvicorn>=0.20.0; extra == 'caas'
Provides-Extra: cmvk
Requires-Dist: numpy>=1.20.0; extra == 'cmvk'
Provides-Extra: control-plane
Provides-Extra: core
Requires-Dist: agent-os[cmvk,control-plane,primitives]; extra == 'core'
Provides-Extra: dev
Requires-Dist: black>=23.0.0; extra == 'dev'
Requires-Dist: mypy>=1.0.0; extra == 'dev'
Requires-Dist: pytest-asyncio>=0.21.0; extra == 'dev'
Requires-Dist: pytest-cov>=4.0.0; extra == 'dev'
Requires-Dist: pytest>=7.0.0; extra == 'dev'
Requires-Dist: ruff>=0.1.0; extra == 'dev'
Provides-Extra: docs
Requires-Dist: mkdocs-material>=9.0.0; extra == 'docs'
Requires-Dist: mkdocs>=1.5.0; extra == 'docs'
Requires-Dist: mkdocstrings[python]>=0.24.0; extra == 'docs'
Provides-Extra: emk
Requires-Dist: chromadb>=0.4.0; extra == 'emk'
Requires-Dist: numpy>=1.20.0; extra == 'emk'
Provides-Extra: full
Requires-Dist: agent-os[amb,atr,caas,cmvk,control-plane,emk,iatp,mute-agent,primitives,scak]; extra == 'full'
Provides-Extra: iatp
Requires-Dist: fastapi>=0.100.0; extra == 'iatp'
Requires-Dist: httpx>=0.24.0; extra == 'iatp'
Requires-Dist: uvicorn>=0.20.0; extra == 'iatp'
Provides-Extra: infrastructure
Requires-Dist: agent-os[amb,atr,iatp]; extra == 'infrastructure'
Provides-Extra: intelligence
Requires-Dist: agent-os[mute-agent,scak]; extra == 'intelligence'
Provides-Extra: mute-agent
Provides-Extra: primitives
Provides-Extra: scak
Requires-Dist: pyyaml>=6.0; extra == 'scak'
